banana/__about__.py
banana/__init__.py
banana/bids_.py
banana/citation.py
banana/entrypoint.py
banana/exceptions.py
banana/file_format.py
banana/plot.py
banana/requirement.py
banana/analysis/__init__.py
banana/analysis/base.py
banana/analysis/mri/__init__.py
banana/analysis/mri/base.py
banana/analysis/mri/bold.py
banana/analysis/mri/dwi.py
banana/analysis/mri/epi.py
banana/analysis/mri/multi.py
banana/analysis/mri/t1w.py
banana/analysis/mri/t2star.py
banana/analysis/mri/t2w.py
banana/analysis/multi/__init__.py
banana/analysis/multi/mrpet.py
banana/analysis/pet/__init__.py
banana/analysis/pet/base.py
banana/analysis/pet/dynamic.py
banana/analysis/pet/static.py
banana/interfaces/__init__.py
banana/interfaces/afni.py
banana/interfaces/ants.py
banana/interfaces/bold.py
banana/interfaces/c3d.py
banana/interfaces/converters.py
banana/interfaces/dicom.py
banana/interfaces/dwi.py
banana/interfaces/freesurfer.py
banana/interfaces/fsl.py
banana/interfaces/kspace.py
banana/interfaces/mask.py
banana/interfaces/matlab.py
banana/interfaces/motion_correction.py
banana/interfaces/noddi.py
banana/interfaces/pet.py
banana/interfaces/phase.py
banana/interfaces/qsm.py
banana/interfaces/scipy.py
banana/interfaces/sklearn.py
banana/interfaces/spm.py
banana/interfaces/sti.py
banana/interfaces/umap_calc.py
banana/interfaces/utility.py
banana/interfaces/vein_analysis.py
banana/interfaces/custom/__init__.py
banana/interfaces/custom/bold.py
banana/interfaces/custom/coils.py
banana/interfaces/custom/dicom.py
banana/interfaces/custom/dwi.py
banana/interfaces/custom/mask.py
banana/interfaces/custom/motion_correction.py
banana/interfaces/custom/pet.py
banana/interfaces/custom/vein_analysis.py
banana/interfaces/mrtrix/__init__.py
banana/interfaces/mrtrix/fibre_est.py
banana/interfaces/mrtrix/preproc.py
banana/interfaces/mrtrix/tracking.py
banana/interfaces/mrtrix/transform.py
banana/interfaces/mrtrix/utils.py
banana/interfaces/sti/__init__.py
banana/interfaces/sti/base.py
banana-0.5.1.dist-info/AUTHORS
banana-0.5.1.dist-info/LICENSE
banana-0.5.1.dist-info/METADATA
banana-0.5.1.dist-info/WHEEL
banana-0.5.1.dist-info/entry_points.txt
banana-0.5.1.dist-info/top_level.txt
banana-0.5.1.dist-info/RECORD
