Metadata-Version: 2.1
Name: banana
Version: 0.5.1
Summary: Brain imAgiNg Analysis iN Arcana (Banana): brain imaging analysis workflows implemented in the Arcana framework (arcana.readthedocs.io)
Home-page: https://github.com/MonashBI/banana
Author: Tom G. Close
Author-email: tom.g.close@gmail.com
License: The Apache Software Licence 2.0
Platform: UNKNOWN
Classifier: Development Status :: 4 - Beta
Classifier: Intended Audience :: Healthcare Industry
Classifier: Intended Audience :: Science/Research
Classifier: License :: OSI Approved :: Apache Software License
Classifier: Natural Language :: English
Classifier: Programming Language :: Python :: 3.4
Classifier: Programming Language :: Python :: 3.5
Classifier: Programming Language :: Python :: 3.6
Classifier: Programming Language :: Python :: 3.7
Classifier: Topic :: Scientific/Engineering :: Bio-Informatics
Classifier: Topic :: Scientific/Engineering :: Medical Science Apps.
Requires-Dist: arcana (>=0.6.1)
Requires-Dist: pydicom (>=1.0)
Requires-Dist: nibabel (>=2.3.0)
Requires-Dist: pybids (>=0.9.1)
Requires-Dist: scipy (>=1.1.0)
